dupln/__init__.py
dupln/__main__.py
dupln/findskel.py
dupln/main.py
dupln/walkdir.py
dupln-0.1.2.dist-info/licenses/LICENSE
dupln-0.1.2.dist-info/METADATA
dupln-0.1.2.dist-info/WHEEL
dupln-0.1.2.dist-info/entry_points.txt
dupln-0.1.2.dist-info/top_level.txt
dupln-0.1.2.dist-info/RECORD
